confile/__init__.py
confile/confile.py
tests/__init__.py
tests/test_confile.py
confile-1.4.dist-info/LICENSE
confile-1.4.dist-info/METADATA
confile-1.4.dist-info/WHEEL
confile-1.4.dist-info/top_level.txt
confile-1.4.dist-info/RECORD
