Metadata-Version: 2.1
Name: confile
Version: 1.4
Summary: confile: config file reader
Home-page: https://github.com/777nancy/confile
Author: 777nancy
Author-email: ys.5.mil.7@gmail.com
License: MIT License
Platform: UNKNOWN
Classifier: Programming Language :: Python :: 3
Classifier: Programming Language :: Python :: 3.6
Classifier: Programming Language :: Python :: 3.7
Classifier: Programming Language :: Python :: 3.8
Classifier: License :: OSI Approved :: MIT License
Requires-Python: >=3.6
Requires-Dist: PyYAML (>=5.3.1)
